beelzebub/base/__init__.py
beelzebub/base/__main__.py
beelzebub-1.0.0.dist-info/LICENSE
beelzebub-1.0.0.dist-info/WHEEL
beelzebub-1.0.0.dist-info/METADATA
beelzebub-1.0.0.dist-info/RECORD
