Metadata-Version: 2.1
Name: beelzebub
Version: 1.0.0
Summary: Lightweight framework for transforming input to output
Home-page: https://github.com/paul-breen/beelzebub
License: Apache-2.0
Author: Paul Breen
Author-email: paul.breen6@btinternet.com
Requires-Python: >=3.8,<4.0
Classifier: License :: OSI Approved :: Apache Software License
Classifier: Programming Language :: Python :: 3
Classifier: Programming Language :: Python :: 3.8
Classifier: Programming Language :: Python :: 3.9
Classifier: Programming Language :: Python :: 3.10
Classifier: Programming Language :: Python :: 3.11
Requires-Dist: Jinja2 (>=3.1.0,<4.0.0)
Requires-Dist: aiohttp (>=3.10.11,<4.0.0)
Requires-Dist: fsspec (>=2024.10.0,<2025.0.0)
Requires-Dist: requests (>=2.32.3,<3.0.0)
Project-URL: Documentation, https://github.com/paul-breen/beelzebub/blob/main/README.md
Project-URL: Repository, https://github.com/paul-breen/beelzebub
